flown/__init__.py
flown/__version__.py
flown/cli.py
flown/project_store.py
flown/api/__init__.py
flown/api/wrapper_for_notebook.py
flown/template/_layout.html
flown/template/_loading.html
flown/template/artifact_viewer.html
flown/template/experiment_detail.html
flown/template/experiment_list.html
flown/template/markdown_editor.html
flown/template/run_detail.html
flown/template/text_editor.html
flown/utils/__init__.py
flown/utils/artifact_util.py
flown/utils/compat.py
flown/utils/image_util.py
flown/utils/s3util.py
flown-0.1.0.dist-info/LICENSE.txt
flown-0.1.0.dist-info/METADATA
flown-0.1.0.dist-info/WHEEL
flown-0.1.0.dist-info/entry_points.txt
flown-0.1.0.dist-info/top_level.txt
flown-0.1.0.dist-info/RECORD
