Metadata-Version: 2.1
Name: flown
Version: 0.1.0
Summary: Notebook friendly MLflow viewer
Home-page: https://github.com/advtec/flown
Maintainer: takagi, tokoi
Maintainer-email: takagi.motoshige@gmail.com, mkt.tokoi@gmail.com
License: MIT
Keywords: mlflow,experiment manager,jupyter-notebook,jupyter-lab
Platform: UNKNOWN
Classifier: Framework :: Flask
Classifier: Programming Language :: Python :: 3
Classifier: Programming Language :: Python :: 3.6
Classifier: License :: OSI Approved :: MIT License
License-File: LICENSE.txt
Requires-Dist: mlflow (~=1.17.0)
Requires-Dist: click (~=8.0.1)
Requires-Dist: boto3
Requires-Dist: mlflow
Requires-Dist: Jinja2 (~=3.0.1)
Requires-Dist: markdown (~=3.3.4)
